dj_paynow-0.0.1.dist-info/licenses/LICENSE
paynow/__init__.py
paynow/admin.py
paynow/apps.py
paynow/cli.py
paynow/conf.py
paynow/exceptions.py
paynow/forms.py
paynow/models.py
paynow/paynow_client.py
paynow/serializers.py
paynow/signals.py
paynow/urls.py
paynow/utils.py
paynow/views.py
paynow/templates/paynow/payment_detail.html
paynow/templates/paynow/payment_error.html
paynow/templates/paynow/payment_pending.html
paynow/templates/paynow/payment_success.html
dj_paynow-0.0.1.dist-info/METADATA
dj_paynow-0.0.1.dist-info/WHEEL
dj_paynow-0.0.1.dist-info/top_level.txt
dj_paynow-0.0.1.dist-info/RECORD
