Metadata-Version: 2.4
Name: dj-paynow
Version: 0.0.1
Summary: Django Paynow integration library for South African payments
Home-page: https://github.com/carrington-dev/dj-paynow
Author: Carrington Muleya
Author-email: Carrington Muleya <carrington.muleya@outlook.com>
License: MIT
Project-URL: Homepage, https://github.com/carrington-dev/dj-paynow
Project-URL: Documentation, https://dj-paynow.github.io/dj-paynow/
Project-URL: Repository, https://github.com/carrington-dev/dj-paynow
Project-URL: Bug Tracker, https://github.com/carrington-dev/dj-paynow/issues
Keywords: django,paynow,payment,gateway,south-africa
Classifier: Development Status :: 4 - Beta
Classifier: Framework :: Django
Classifier: Framework :: Django :: 3.2
Classifier: Framework :: Django :: 4.0
Classifier: Framework :: Django :: 4.1
Classifier: Framework :: Django :: 4.2
Classifier: Framework :: Django :: 5.0
Classifier: Intended Audience :: Developers
Classifier: License :: OSI Approved :: MIT License
Classifier: Programming Language :: Python :: 3
Classifier: Programming Language :: Python :: 3.8
Classifier: Programming Language :: Python :: 3.9
Classifier: Programming Language :: Python :: 3.10
Classifier: Programming Language :: Python :: 3.11
Classifier: Programming Language :: Python :: 3.12
Requires-Python: >=3.8
License-File: LICENSE
Requires-Dist: Django>=3.2
Requires-Dist: djangorestframework
Requires-Dist: requests>=2.25.0
Provides-Extra: dev
Requires-Dist: pytest>=7.0.0; extra == "dev"
Requires-Dist: pytest-django>=4.5.0; extra == "dev"
Requires-Dist: pytest-cov>=4.0.0; extra == "dev"
Requires-Dist: black>=22.0.0; extra == "dev"
Requires-Dist: flake8>=5.0.0; extra == "dev"
Requires-Dist: isort>=5.10.0; extra == "dev"
Provides-Extra: docs
Requires-Dist: sphinx>=5.0.0; extra == "docs"
Requires-Dist: sphinx-rtd-theme>=1.0.0; extra == "docs"
Dynamic: author
Dynamic: home-page
Dynamic: license-file
Dynamic: requires-python
